Metadata-Version: 2.1
Name: aiohook
Version: 0.1.2
Summary: A simple plugin system for async applications
Home-page: https://github.com/agravier/aiohook
Author: Alexandre Gravier
Author-email: al.gravier@gmail.com
License: UNKNOWN
Keywords: plugin,hook,async,asyncio,trio,curio
Platform: UNKNOWN
Classifier: Development Status :: 2 - Pre-Alpha
Classifier: Environment :: Plugins
Classifier: Intended Audience :: Developers
Classifier: License :: OSI Approved :: GNU Lesser General Public License v3 (LGPLv3)
Classifier: Topic :: Software Development :: Libraries
Classifier: Programming Language :: Python :: 3 :: Only
Classifier: Programming Language :: Python :: 3.7
